{"time_collected": "2023-03-08 15:42:44.465087-05:00", "top_headers": [{"heading": "DALE CAMPE\u00d3N!!!", "time_posted": "1 year ago"}, {"heading": "[PMT] River Plate vs Lan\u00fas (Fecha 06 - Torneo LPF 2023)", "time_posted": "4 days ago"}, {"heading": "Puede ser tan mala la atenci\u00f3n al socio?", "time_posted": "6 hours ago"}, {"heading": "Hola millos! Este domingo, a sus 67 a\u00f1os, voy a poder cumplirle el sue\u00f1o a vieja de conocer el monumental. De s\u00f3lo ver su emoci\u00f3n me llena de emoci\u00f3n a m\u00ed. Quer\u00eda compartirlo con ustedes que entienden el sentimiento. \u2764\ufe0f", "time_posted": "21 hours ago"}, {"heading": "Venta de las viejas butacas", "time_posted": "23 hours ago"}, {"heading": "Soy yo o est\u00e1n tratando de matar definitivamente a SomosRiver?", "time_posted": "1 day ago"}, {"heading": "D\u00edas de la venta de entradas para el partido con Godoy Cruz", "time_posted": "2 days ago"}], "rules": ["Trolling", "Xenophobia", "Rediiquette breach"], "subreddits": {}, "about": {"header": "About Community", "description": "A Subreddit dedicated to the best Argentine football/soccer club: Club Atl\u00e9tico River Plate.", "created": "Created Oct 18, 2011", "stats": ["6.2k Millonarios", "7 Online"]}, "other_information": [{"header": "Links", "description": "River Plate (Oficial)\nYouTube - River Plate (Oficial)\nLa Pagina Millonaria\nTelegram"}], "type": "public"}