{"time_collected": "2023-03-19 22:25:38.753026-04:00", "top_headers": [{"heading": "Como voc\u00eas acham que Maegor morreu?", "time_posted": "1 day ago"}, {"heading": "Jaehaerys II e Shaera Targaryen por chillyravenart", "time_posted": "1 day ago"}, {"heading": "Game of Thrones: A casa Tully \u00e9 leal a quem agora?", "time_posted": "2 days ago"}, {"heading": "D\u00e1 pra controlar drag\u00f5es com m\u00fasica?", "time_posted": "2 days ago"}, {"heading": "Danny Flint tornou-se M\u00e3os Frias ap\u00f3s morrer", "time_posted": "3 days ago"}, {"heading": "Tem que admirar a coragem, pois ju\u00edzo n\u00e3o tem", "time_posted": "3 days ago"}], "rules": ["Cuidado com off-topic.", "Obede\u00e7a a Pol\u00edtica de Spoiler.", "Tenha tato ao falar de viol\u00eancia sexual.", "Coloque o flair adequado em seu post. (Regra temporariamente inv\u00e1lida)", "Seja civilizado.", "N\u00e3o repita t\u00f3picos de vazamentos.", "Coloque cr\u00e9dito e fontes nas artes."], "subreddits": {"Subreddits parceiros": {"r/rpg_brasil": "107,202 members", "r/brasil": "1,356,485 members", "r/filmeseseries": "94,112 members"}}, "about": {"header": "About Community", "description": "Dedicado \u00e0s Cr\u00f4nicas de Gelo e Fogo (ASOIAF), demais obras de George R. R. Martin e suas adapta\u00e7\u00f5es (Game of Thrones, House of The Dragon). Posts em portugu\u00eas, ingl\u00eas ou espanhol.", "created": "Created Jun 23, 2019", "stats": ["2.0k Members", "6 Online"]}, "other_information": [], "type": "public"}